CHANGELOG.txt
LICENSE.txt
MANIFEST.in
README.txt
setup.py
basic_cal/__init__.py
ravisimplemodule.egg-info/PKG-INFO
ravisimplemodule.egg-info/SOURCES.txt
ravisimplemodule.egg-info/dependency_links.txt
ravisimplemodule.egg-info/top_level.txt